heaserver/trashawss3/__init__.py
heaserver/trashawss3/service.py
heaserver/trashawss3/wstl/all.json
heaserver_trash_aws_s3-1.1.3.dist-info/LICENSE
heaserver_trash_aws_s3-1.1.3.dist-info/METADATA
heaserver_trash_aws_s3-1.1.3.dist-info/WHEEL
heaserver_trash_aws_s3-1.1.3.dist-info/entry_points.txt
heaserver_trash_aws_s3-1.1.3.dist-info/top_level.txt
heaserver_trash_aws_s3-1.1.3.dist-info/RECORD
