Metadata-Version: 2.1
Name: heaserver-trash-aws-s3
Version: 1.1.3
Summary: Deleted file management
Home-page: https://risr.hci.utah.edu
Author: Research Informatics Shared Resource, Huntsman Cancer Institute, Salt Lake City, UT
Author-email: Andrew.Post@hci.utah.edu
Keywords: heaserver-trash-aws-s3,microservice,healthcare,cancer,research,informatics
Classifier: Development Status :: 5 - Production/Stable
Classifier: Environment :: Console
Classifier: Intended Audience :: Developers
Classifier: Natural Language :: English
Classifier: License :: OSI Approved :: Apache Software License
Classifier: Operating System :: OS Independent
Classifier: Programming Language :: Python
Classifier: Programming Language :: Python :: 3
Classifier: Programming Language :: Python :: 3.10
Classifier: Programming Language :: Python :: 3.11
Classifier: Programming Language :: Python :: Implementation :: CPython
Classifier: Topic :: Software Development
Classifier: Topic :: Scientific/Engineering
Classifier: Topic :: Scientific/Engineering :: Bio-Informatics
Classifier: Topic :: Scientific/Engineering :: Information Analysis
Classifier: Topic :: Scientific/Engineering :: Medical Science Apps.
Requires-Python: >=3.10
License-File: LICENSE
Requires-Dist: heaserver ~=1.8.3
Requires-Dist: aiostream ~=0.5.1
